COPYING
MANIFEST.in
README
VERSION
chkfs
chkfs.py
run_tests_with_coverage.sh
setup.py
test_chkfs.py
chkfs.egg-info/PKG-INFO
chkfs.egg-info/SOURCES.txt
chkfs.egg-info/dependency_links.txt
chkfs.egg-info/requires.txt
chkfs.egg-info/top_level.txt