Metadata-Version: 1.0
Name: chkfs
Version: 0.990c613daa19960e8a900cbffc5472e44282b6f1
Summary: A commandline tool for storing filesystems inside a chkstore.
Home-page: https://bitbucket.org/nejucomo/chkfs
Author: Nathan Wilcox
Author-email: nejucomo@gmail.com
License: GPLv3
Platform: UNKNOWN
